setup.py
mvs_distributions/Binomialdistribution.py
mvs_distributions/Gaussiandistribution.py
mvs_distributions/Generaldistribution.py
mvs_distributions/__init__.py
mvs_distributions.egg-info/PKG-INFO
mvs_distributions.egg-info/SOURCES.txt
mvs_distributions.egg-info/dependency_links.txt
mvs_distributions.egg-info/not-zip-safe
mvs_distributions.egg-info/top_level.txt