Metadata-Version: 1.0
Name: mvs-distributions
Version: 0.15
Summary: Gaussian distributions
Home-page: UNKNOWN
Author: UNKNOWN
Author-email: UNKNOWN
License: UNKNOWN
Platform: UNKNOWN
